nv_one_logger/no_init.md
nv_one_logger/training_recorder.py
nv_one_logger/training_telemetry/api/__init__.py
nv_one_logger/training_telemetry/api/attributes.py
nv_one_logger/training_telemetry/api/callbacks.py
nv_one_logger/training_telemetry/api/checkpoint.py
nv_one_logger/training_telemetry/api/config.py
nv_one_logger/training_telemetry/api/context.py
nv_one_logger/training_telemetry/api/events.py
nv_one_logger/training_telemetry/api/spans.py
nv_one_logger/training_telemetry/api/training_recorder.py
nv_one_logger/training_telemetry/api/training_telemetry_provider.py
nv_one_logger/training_telemetry/docs/example.py
nv_one_logger_training_telemetry-2.3.0.dist-info/LICENSE
nv_one_logger_training_telemetry-2.3.0.dist-info/METADATA
nv_one_logger_training_telemetry-2.3.0.dist-info/WHEEL
nv_one_logger_training_telemetry-2.3.0.dist-info/RECORD
